revscoring/__init__.py
revscoring/about.py
revscoring/errors.py
revscoring/revscoring.py
revscoring/score_processor.py
revscoring/assets/enwiktionary_idioms.txt
revscoring/datasources/__init__.py
revscoring/datasources/datasource.py
revscoring/datasources/revision_oriented.py
revscoring/datasources/meta/__init__.py
revscoring/datasources/meta/dicts.py
revscoring/datasources/meta/extractors.py
revscoring/datasources/meta/filters.py
revscoring/datasources/meta/frequencies.py
revscoring/datasources/meta/gramming.py
revscoring/datasources/meta/hashing.py
revscoring/datasources/meta/indexable.py
revscoring/datasources/meta/mappers.py
revscoring/datasources/meta/selectors.py
revscoring/datasources/meta/timestamp.py
revscoring/datasources/meta/vectorizers.py
revscoring/dependencies/__init__.py
revscoring/dependencies/context.py
revscoring/dependencies/dependent.py
revscoring/dependencies/functions.py
revscoring/dependencies/util.py
revscoring/extractors/__init__.py
revscoring/extractors/extractor.py
revscoring/extractors/api/__init__.py
revscoring/extractors/api/datasources.py
revscoring/extractors/api/extractor.py
revscoring/extractors/api/revision_oriented.py
revscoring/extractors/api/util.py
revscoring/features/__init__.py
revscoring/features/feature.py
revscoring/features/feature_vector.py
revscoring/features/functions.py
revscoring/features/modifiers.py
revscoring/features/revision_oriented.py
revscoring/features/util.py
revscoring/features/bytes/__init__.py
revscoring/features/bytes/datasources.py
revscoring/features/bytes/revision_oriented.py
revscoring/features/meta/__init__.py
revscoring/features/meta/aggregators.py
revscoring/features/meta/bools.py
revscoring/features/meta/vectorizers.py
revscoring/features/temporal/__init__.py
revscoring/features/temporal/revision_oriented.py
revscoring/features/wikibase/__init__.py
revscoring/features/wikibase/revision_oriented.py
revscoring/features/wikibase/util.py
revscoring/features/wikibase/datasources/__init__.py
revscoring-2.11.13.dist-info/LICENSE
revscoring-2.11.13.dist-info/METADATA
revscoring-2.11.13.dist-info/WHEEL
revscoring-2.11.13.dist-info/entry_points.txt
revscoring-2.11.13.dist-info/top_level.txt
revscoring-2.11.13.dist-info/RECORD
