Metadata-Version: 2.1
Name: revscoring
Version: 2.11.13
Summary: A set of utilities for generating quality scores for MediaWiki revisions
Home-page: https://github.com/wikimedia/revscoring
Author: Aaron Halfaker
Author-email: ahalfaker@wikimedia.org
License: MIT
Classifier: Development Status :: 3 - Alpha
Classifier: Programming Language :: Python
Classifier: Programming Language :: Python :: 3
Classifier: Environment :: Other Environment
Classifier: Intended Audience :: Developers
Classifier: License :: OSI Approved :: MIT License
Classifier: Operating System :: OS Independent
Requires-Python: >=3
License-File: LICENSE
Requires-Dist: Cython >=0.28.5
Requires-Dist: deep-merge <0.0.999,>=0.0.1
Requires-Dist: deltas <0.7.999,>=0.7.0
Requires-Dist: docopt <0.6.999,>=0.6.2
Requires-Dist: gensim >=3.8.1
Requires-Dist: hanziconv <0.3.999,>=0.3.2
Requires-Dist: mmh3 <2.5.999,>=2.5.1
Requires-Dist: more-itertools <7.2.999,>=7.2.0
Requires-Dist: mwapi <0.6.999,>=0.5.0
Requires-Dist: mwbase <0.1.999,>=0.1.4
Requires-Dist: mwtypes <0.3.999,>=0.2.0
Requires-Dist: mwparserfromhell <0.6.999,>=0.6.5
Requires-Dist: mysqltsv <0.0.999,>=0.0.7
Requires-Dist: nltk >=3.6.6
Requires-Dist: numpy <1.25.0,>=1.21.5
Requires-Dist: pytz >=2017.2
Requires-Dist: requests <2.999.999,>=2.0.0
Requires-Dist: pyenchant >=3.2.2
Requires-Dist: scipy <1.10.1,>=1.5.4
Requires-Dist: scikit-learn >=1.0.2
Requires-Dist: tabulate <0.9.999,>=0.9.0
Requires-Dist: tqdm <4.15.9999,>=4.15.0
Requires-Dist: yamlconf-wmf ==0.2.10
Requires-Dist: flashtext ==2.7
